polario/__init__.py
polario/_version.py
polario/delta_dataset.py
polario/hive_dataset.py
polario/main.py
polario/py.typed
polario-0.3.2.dist-info/METADATA
polario-0.3.2.dist-info/WHEEL
polario-0.3.2.dist-info/entry_points.txt
polario-0.3.2.dist-info/licenses/LICENSE
polario-0.3.2.dist-info/RECORD
