Metadata-Version: 2.3
Name: polario
Version: 0.3.2
Summary: Polars IO
Project-URL: homepage, https://bneijt.github.io/polario/
Project-URL: repository, https://github.com/bneijt/polario
Author-email: Bram Neijt <bram@neijt.nl>
License: Apache-2.0
Classifier: Intended Audience :: Developers
Classifier: License :: OSI Approved :: Apache Software License
Classifier: Programming Language :: Python :: 3
Requires-Python: >=3.9
Requires-Dist: fsspec
Requires-Dist: polars[fsspec]>=0.16
Requires-Dist: pyarrow>11
